{
  "latestVersionCode": 27,
  "latestVersionName": "1.9.2",
  "apkUrl": "https://github.com/atri1011/music/releases/download/v1.9.2/app-release.apk",
  "sha256": "131075c557e817a48882ff4bfac6c2dd83b0b644968f9e6d63950867256d58c9",
  "fileSizeBytes": 43676830,
  "changelog": "**Full Changelog**: https://github.com/atri1011/music/compare/v1.9.1...v1.9.2",
  "fullChangelogUrl": "https://github.com/atri1011/music/compare/v1.9.1...v1.9.2",
  "isForceUpdate": false,
  "minSupportedVersionCode": 0,
  "publishedAt": "2026-06-11T06:09:02Z"
}
